MANIFEST.in
setup.cfg
setup.py
surveilr/__init__.py
surveilr/config.py
surveilr/defaults.cfg
surveilr/drivers.py
surveilr/exceptions.py
surveilr/models.py
surveilr/utils.py
surveilr.egg-info/PKG-INFO
surveilr.egg-info/SOURCES.txt
surveilr.egg-info/dependency_links.txt
surveilr.egg-info/requires.txt
surveilr.egg-info/top_level.txt
surveilr/tests/test_config_config.cfg
surveilr/tests/test_config_defaults.cfg
surveilr/tests/test_messaging.cfg