Metadata-Version: 1.0
Name: surveilr
Version: 0.1a1
Summary: Monitoring System evolved
Home-page: http://surveilr.org/
Author: Soren Hansen
Author-email: soren@linux2go.dk
License: AGPL
Platform: UNKNOWN
Classifier: Development Status :: 2 - Pre-Alpha
Classifier: Environment :: Console
Classifier: Environment :: No Input/Output (Daemon)
Classifier: Intended Audience :: Information Technology
Classifier: Intended Audience :: System Administrators
Classifier: License :: OSI Approved :: GNU Affero General Public License v3
Classifier: Operating System :: POSIX :: Linux
Classifier: Programming Language :: Python
Classifier: Topic :: Internet :: Log Analysis
Classifier: Topic :: System :: Monitoring
Classifier: Topic :: System :: Networking :: Monitoring
